NRDD/NRDD_constraints.py
NRDD/NRDD_data1.npy
NRDD/NRDD_data2.npy
NRDD/__init__.py
NRDD/_version.py
NRDD-2.7.1.dist-info/LICENSE
NRDD-2.7.1.dist-info/METADATA
NRDD-2.7.1.dist-info/WHEEL
NRDD-2.7.1.dist-info/top_level.txt
NRDD-2.7.1.dist-info/RECORD
