Metadata-Version: 2.1
Name: NRDD
Version: 2.7.1
Summary: A python tool for calculating the direct-detection exclusion plot for the WIMP-nucleon cross section in a non-relativistic effective model
Home-page: https://github.com/NRDD-constraints/NRDD
Author: Stefano Scopel, Gaurav Tomar, Jong Hyun Yoon, Sunghyun Kang
Author-email: scopel@sogang.ac.kr
License: MIT
Platform: UNKNOWN
Requires-Dist: numpy
Requires-Dist: scipy
Requires-Dist: setuptools
